{"label": "one-to-n_N1", "mode": "one-to-n", "M": 1, "N": 1, "metrics": {"model_mix_latency": {"p50_us": 335.563, "p95_us": 340.807, "p99_us": 347.125, "max_us": 2408.953, "gate": "yellow"}, "h2d_us": {"p50_us": 20.8, "p95_us": 23.36, "p99_us": 26.528, "max_us": 353.695, "gate": "n/a"}, "kernel_us": {"p50_us": 4.672, "p95_us": 4.767, "p99_us": 4.767, "max_us": 608.352, "gate": "n/a"}, "d2h_us": {"p50_us": 16.607, "p95_us": 17.664, "p99_us": 17.696, "max_us": 20.767, "gate": "n/a"}, "gpu_process_us": {"p50_us": 53.907, "p95_us": 55.031, "p99_us": 57.918, "max_us": 1274.329, "gate": "n/a"}}, "backend": "cuda", "iterations": 29688, "gpu_snap": {"mem_used_MiB": 1091, "mem_delta_MiB": 508, "pcie_gen": "5", "pcie_width": "4", "util_gpu_pct": 10, "util_mem_pct": 0, "graphics_clock_MHz": 2392, "mem_clock_MHz": 13801, "power_W": 49.98}, "nsys_error": "invalid literal for int() with base 10: '1736.1'"}
{"label": "one-to-n_N2", "mode": "one-to-n", "M": 1, "N": 2, "metrics": {"model_mix_latency": {"p50_us": 337.225, "p95_us": 638.803, "p99_us": 644.112, "max_us": 1516.335, "gate": "red"}, "h2d_us": {"p50_us": 22.112, "p95_us": 39.935, "p99_us": 40.383, "max_us": 104.671, "gate": "n/a"}, "kernel_us": {"p50_us": 4.639, "p95_us": 4.736, "p99_us": 4.767, "max_us": 192.256, "gate": "n/a"}, "d2h_us": {"p50_us": 15.647, "p95_us": 18.656, "p99_us": 19.711, "max_us": 20.767, "gate": "n/a"}, "gpu_process_us": {"p50_us": 54.612, "p95_us": 74.689, "p99_us": 75.625, "max_us": 713.782, "gate": "n/a"}}, "backend": "cuda", "iterations": 22956, "gpu_snap": {"mem_used_MiB": 1091, "mem_delta_MiB": 508, "pcie_gen": "5", "pcie_width": "4", "util_gpu_pct": 9, "util_mem_pct": 0, "graphics_clock_MHz": 2392, "mem_clock_MHz": 13801, "power_W": 50.04}, "nsys_error": "invalid literal for int() with base 10: '2033.0'"}
{"label": "one-to-n_N4", "mode": "one-to-n", "M": 1, "N": 4, "metrics": {"model_mix_latency": {"p50_us": 335.033, "p95_us": 1222.709, "p99_us": 1228.581, "max_us": 1776.29, "gate": "red"}, "h2d_us": {"p50_us": 21.312, "p95_us": 64.479, "p99_us": 67.808, "max_us": 94.719, "gate": "n/a"}, "kernel_us": {"p50_us": 4.672, "p95_us": 6.655, "p99_us": 6.688, "max_us": 182.4, "gate": "n/a"}, "d2h_us": {"p50_us": 16.64, "p95_us": 18.688, "p99_us": 20.735, "max_us": 20.767, "gate": "n/a"}, "gpu_process_us": {"p50_us": 54.709, "p95_us": 100.752, "p99_us": 102.909, "max_us": 281.672, "gate": "n/a"}}, "backend": "cuda", "iterations": 19520, "gpu_snap": {"mem_used_MiB": 1093, "mem_delta_MiB": 510, "pcie_gen": "5", "pcie_width": "4", "util_gpu_pct": 8, "util_mem_pct": 0, "graphics_clock_MHz": 2392, "mem_clock_MHz": 13801, "power_W": 49.81}, "nsys_error": "invalid literal for int() with base 10: '2214.7'"}
{"label": "one-to-n_N8", "mode": "one-to-n", "M": 1, "N": 8, "metrics": {"model_mix_latency": {"p50_us": 336.295, "p95_us": 2398.502, "p99_us": 2407.252, "max_us": 3100.222, "gate": "red"}, "h2d_us": {"p50_us": 22.304, "p95_us": 115.616, "p99_us": 119.039, "max_us": 516.48, "gate": "n/a"}, "kernel_us": {"p50_us": 4.639, "p95_us": 8.736, "p99_us": 10.304, "max_us": 125.055, "gate": "n/a"}, "d2h_us": {"p50_us": 14.976, "p95_us": 17.664, "p99_us": 18.015, "max_us": 20.735, "gate": "n/a"}, "gpu_process_us": {"p50_us": 55.566, "p95_us": 153.171, "p99_us": 156.809, "max_us": 573.238, "gate": "n/a"}}, "backend": "cuda", "iterations": 17676, "gpu_snap": {"mem_used_MiB": 1099, "mem_delta_MiB": 516, "pcie_gen": "5", "pcie_width": "4", "util_gpu_pct": 8, "util_mem_pct": 0, "graphics_clock_MHz": 2392, "mem_clock_MHz": 13801, "power_W": 49.83}, "nsys_error": "invalid literal for int() with base 10: '2358.4'"}
{"label": "one-to-n_N16", "mode": "one-to-n", "M": 1, "N": 16, "metrics": {"model_mix_latency": {"p50_us": 336.197, "p95_us": 4754.068, "p99_us": 4770.634, "max_us": 5546.901, "gate": "red"}, "h2d_us": {"p50_us": 22.304, "p95_us": 223.296, "p99_us": 228.351, "max_us": 294.528, "gate": "n/a"}, "kernel_us": {"p50_us": 4.639, "p95_us": 16.383, "p99_us": 16.896, "max_us": 96.896, "gate": "n/a"}, "d2h_us": {"p50_us": 15.584, "p95_us": 17.696, "p99_us": 18.015, "max_us": 21.152, "gate": "n/a"}, "gpu_process_us": {"p50_us": 55.735, "p95_us": 269.978, "p99_us": 275.143, "max_us": 363.032, "gate": "n/a"}}, "backend": "cuda", "iterations": 16762, "gpu_snap": {"mem_used_MiB": 1113, "mem_delta_MiB": 530, "pcie_gen": "5", "pcie_width": "4", "util_gpu_pct": 8, "util_mem_pct": 0, "graphics_clock_MHz": 2392, "mem_clock_MHz": 13801, "power_W": 50.05}, "nsys_error": "invalid literal for int() with base 10: '2467.4'"}
{"label": "one-to-n_N32", "mode": "one-to-n", "M": 1, "N": 32, "metrics": {"model_mix_latency": {"p50_us": 335.896, "p95_us": 342.607, "p99_us": 9492.058, "max_us": 10389.651, "gate": "red"}, "h2d_us": {"p50_us": 22.336, "p95_us": 26.784, "p99_us": 445.376, "max_us": 451.2, "gate": "n/a"}, "kernel_us": {"p50_us": 4.639, "p95_us": 4.767, "p99_us": 29.152, "max_us": 116.191, "gate": "n/a"}, "d2h_us": {"p50_us": 15.584, "p95_us": 17.696, "p99_us": 18.015, "max_us": 21.056, "gate": "n/a"}, "gpu_process_us": {"p50_us": 55.549, "p95_us": 59.317, "p99_us": 506.327, "max_us": 592.651, "gate": "n/a"}}, "backend": "cuda", "iterations": 16302, "gpu_snap": {"mem_used_MiB": 1133, "mem_delta_MiB": 550, "pcie_gen": "5", "pcie_width": "4", "util_gpu_pct": 8, "util_mem_pct": 0, "graphics_clock_MHz": 2392, "mem_clock_MHz": 13801, "power_W": 49.99}, "nsys_error": "invalid literal for int() with base 10: '2518.2'"}
{"label": "one-to-n_N64", "mode": "one-to-n", "M": 1, "N": 64, "metrics": {"model_mix_latency": {"p50_us": 337.288, "p95_us": 343.657, "p99_us": 18926.037, "max_us": 21740.05, "gate": "red"}, "h2d_us": {"p50_us": 23.072, "p95_us": 26.655, "p99_us": 881.247, "max_us": 957.376, "gate": "n/a"}, "kernel_us": {"p50_us": 4.511, "p95_us": 4.736, "p99_us": 53.631, "max_us": 145.759, "gate": "n/a"}, "d2h_us": {"p50_us": 14.592, "p95_us": 17.664, "p99_us": 18.015, "max_us": 21.056, "gate": "n/a"}, "gpu_process_us": {"p50_us": 56.271, "p95_us": 59.79, "p99_us": 968.344, "max_us": 1320.072, "gate": "n/a"}}, "backend": "cuda", "iterations": 15990, "gpu_snap": {"mem_used_MiB": 1181, "mem_delta_MiB": 598, "pcie_gen": "5", "pcie_width": "4", "util_gpu_pct": 8, "util_mem_pct": 0, "graphics_clock_MHz": 2392, "mem_clock_MHz": 13801, "power_W": 50.26}, "nsys_error": "invalid literal for int() with base 10: '2532.6'"}
{"label": "m-to-n_M2_N2", "mode": "m-to-n", "M": 2, "N": 2, "metrics": {"model_mix_latency": {"p50_us": 632.363, "p95_us": 637.329, "p99_us": 643.201, "max_us": 1481.169, "gate": "red"}, "h2d_us": {"p50_us": 38.047, "p95_us": 40.32, "p99_us": 40.543, "max_us": 110.335, "gate": "n/a"}, "kernel_us": {"p50_us": 4.639, "p95_us": 4.767, "p99_us": 5.824, "max_us": 237.471, "gate": "n/a"}, "d2h_us": {"p50_us": 15.968, "p95_us": 19.711, "p99_us": 20.735, "max_us": 21.247, "gate": "n/a"}, "gpu_process_us": {"p50_us": 72.871, "p95_us": 75.64, "p99_us": 76.343, "max_us": 312.593, "gate": "n/a"}}, "backend": "cuda", "iterations": 15844, "gpu_snap": {"mem_used_MiB": 1093, "mem_delta_MiB": 510, "pcie_gen": "5", "pcie_width": "4", "util_gpu_pct": 8, "util_mem_pct": 0, "graphics_clock_MHz": 2392, "mem_clock_MHz": 13801, "power_W": 50.01}, "nsys_error": "invalid literal for int() with base 10: '2557.2'"}
{"label": "m-to-n_M4_N4", "mode": "m-to-n", "M": 4, "N": 4, "metrics": {"model_mix_latency": {"p50_us": 1223.54, "p95_us": 1231.811, "p99_us": 1237.243, "max_us": 1434.227, "gate": "red"}, "h2d_us": {"p50_us": 62.399, "p95_us": 68.351, "p99_us": 69.151, "max_us": 246.879, "gate": "n/a"}, "kernel_us": {"p50_us": 6.56, "p95_us": 6.688, "p99_us": 6.816, "max_us": 181.344, "gate": "n/a"}, "d2h_us": {"p50_us": 18.335, "p95_us": 20.735, "p99_us": 21.12, "max_us": 21.152, "gate": "n/a"}, "gpu_process_us": {"p50_us": 101.62, "p95_us": 104.14, "p99_us": 104.983, "max_us": 284.08, "gate": "n/a"}}, "backend": "cuda", "iterations": 8176, "gpu_snap": {"mem_used_MiB": 1107, "mem_delta_MiB": 524, "pcie_gen": "5", "pcie_width": "4", "util_gpu_pct": 6, "util_mem_pct": 0, "graphics_clock_MHz": 2392, "mem_clock_MHz": 13801, "power_W": 49.79}, "nsys_error": "invalid literal for int() with base 10: '4122.3'"}
{"label": "m-to-n_M8_N8", "mode": "m-to-n", "M": 8, "N": 8, "metrics": {"model_mix_latency": {"p50_us": 2398.858, "p95_us": 2426.975, "p99_us": 2449.552, "max_us": 3166.662, "gate": "red"}, "h2d_us": {"p50_us": 115.552, "p95_us": 120.255, "p99_us": 122.336, "max_us": 187.616, "gate": "n/a"}, "kernel_us": {"p50_us": 9.887, "p95_us": 10.719, "p99_us": 10.784, "max_us": 138.784, "gate": "n/a"}, "d2h_us": {"p50_us": 14.72, "p95_us": 17.855, "p99_us": 21.023, "max_us": 21.215, "gate": "n/a"}, "gpu_process_us": {"p50_us": 154.009, "p95_us": 161.8, "p99_us": 165.609, "max_us": 296.947, "gate": "n/a"}}, "backend": "cuda", "iterations": 4160, "gpu_snap": {"mem_used_MiB": 1159, "mem_delta_MiB": 576, "pcie_gen": "5", "pcie_width": "4", "util_gpu_pct": 6, "util_mem_pct": 0, "graphics_clock_MHz": 2392, "mem_clock_MHz": 13801, "power_W": 50.01}, "nsys_error": "invalid literal for int() with base 10: '7373.0'"}
{"label": "m-to-n_M16_N16", "mode": "m-to-n", "M": 16, "N": 16, "metrics": {"model_mix_latency": {"p50_us": 4768.272, "p95_us": 4786.245, "p99_us": 4797.531, "max_us": 4947.144, "gate": "red"}, "h2d_us": {"p50_us": 224.224, "p95_us": 230.048, "p99_us": 231.488, "max_us": 312.447, "gate": "n/a"}, "kernel_us": {"p50_us": 16.64, "p95_us": 16.96, "p99_us": 17.055, "max_us": 108.992, "gate": "n/a"}, "d2h_us": {"p50_us": 15.968, "p95_us": 19.071, "p99_us": 21.023, "max_us": 21.471, "gate": "n/a"}, "gpu_process_us": {"p50_us": 273.384, "p95_us": 279.436, "p99_us": 283.871, "max_us": 370.445, "gate": "n/a"}}, "backend": "cuda", "iterations": 2112, "gpu_snap": {"mem_used_MiB": 1371, "mem_delta_MiB": 788, "pcie_gen": "5", "pcie_width": "4", "util_gpu_pct": 5, "util_mem_pct": 0, "graphics_clock_MHz": 2392, "mem_clock_MHz": 13801, "power_W": 50.08}, "nsys_error": "invalid literal for int() with base 10: '13972.5'"}
{"label": "m-to-n_M2_N4", "mode": "m-to-n", "M": 2, "N": 4, "metrics": {"model_mix_latency": {"p50_us": 636.118, "p95_us": 1227.946, "p99_us": 1238.485, "max_us": 1490.508, "gate": "red"}, "h2d_us": {"p50_us": 39.039, "p95_us": 65.343, "p99_us": 68.319, "max_us": 104.511, "gate": "n/a"}, "kernel_us": {"p50_us": 4.703, "p95_us": 6.655, "p99_us": 6.688, "max_us": 178.304, "gate": "n/a"}, "d2h_us": {"p50_us": 17.664, "p95_us": 20.703, "p99_us": 20.896, "max_us": 21.215, "gate": "n/a"}, "gpu_process_us": {"p50_us": 75.138, "p95_us": 102.34, "p99_us": 103.65, "max_us": 277.419, "gate": "n/a"}}, "backend": "cuda", "iterations": 12048, "gpu_snap": {"mem_used_MiB": 1099, "mem_delta_MiB": 516, "pcie_gen": "5", "pcie_width": "4", "util_gpu_pct": 7, "util_mem_pct": 0, "graphics_clock_MHz": 2392, "mem_clock_MHz": 13801, "power_W": 50.19}, "nsys_error": "invalid literal for int() with base 10: '3100.3'"}
{"label": "m-to-n_M2_N8", "mode": "m-to-n", "M": 2, "N": 8, "metrics": {"model_mix_latency": {"p50_us": 636.306, "p95_us": 2406.572, "p99_us": 2418.171, "max_us": 3472.361, "gate": "red"}, "h2d_us": {"p50_us": 38.848, "p95_us": 116.544, "p99_us": 119.903, "max_us": 184.448, "gate": "n/a"}, "kernel_us": {"p50_us": 4.672, "p95_us": 10.048, "p99_us": 10.367, "max_us": 135.327, "gate": "n/a"}, "d2h_us": {"p50_us": 14.911, "p95_us": 20.031, "p99_us": 20.959, "max_us": 91.839, "gate": "n/a"}, "gpu_process_us": {"p50_us": 75.625, "p95_us": 154.737, "p99_us": 158.555, "max_us": 294.651, "gate": "n/a"}}, "backend": "cuda", "iterations": 10130, "gpu_snap": {"mem_used_MiB": 1107, "mem_delta_MiB": 524, "pcie_gen": "5", "pcie_width": "4", "util_gpu_pct": 7, "util_mem_pct": 0, "graphics_clock_MHz": 2392, "mem_clock_MHz": 13801, "power_W": 50.54}, "nsys_error": "invalid literal for int() with base 10: '3511.3'"}
{"label": "m-to-n_M2_N16", "mode": "m-to-n", "M": 2, "N": 16, "metrics": {"model_mix_latency": {"p50_us": 635.748, "p95_us": 4771.368, "p99_us": 4820.065, "max_us": 5838.725, "gate": "red"}, "h2d_us": {"p50_us": 38.336, "p95_us": 224.224, "p99_us": 229.151, "max_us": 232.032, "gate": "n/a"}, "kernel_us": {"p50_us": 4.672, "p95_us": 16.831, "p99_us": 16.896, "max_us": 94.719, "gate": "n/a"}, "d2h_us": {"p50_us": 15.584, "p95_us": 19.711, "p99_us": 20.735, "max_us": 21.247, "gate": "n/a"}, "gpu_process_us": {"p50_us": 74.922, "p95_us": 271.599, "p99_us": 276.617, "max_us": 693.708, "gate": "n/a"}}, "backend": "cuda", "iterations": 9144, "gpu_snap": {"mem_used_MiB": 1129, "mem_delta_MiB": 546, "pcie_gen": "5", "pcie_width": "4", "util_gpu_pct": 6, "util_mem_pct": 0, "graphics_clock_MHz": 2392, "mem_clock_MHz": 13801, "power_W": 50.28}, "nsys_error": "invalid literal for int() with base 10: '3838.7'"}
{"label": "m-to-n_M4_N8", "mode": "m-to-n", "M": 4, "N": 8, "metrics": {"model_mix_latency": {"p50_us": 1238.626, "p95_us": 2431.797, "p99_us": 2452.272, "max_us": 3711.37, "gate": "red"}, "h2d_us": {"p50_us": 64.127, "p95_us": 118.303, "p99_us": 121.151, "max_us": 184.768, "gate": "n/a"}, "kernel_us": {"p50_us": 6.655, "p95_us": 10.463, "p99_us": 10.688, "max_us": 126.24, "gate": "n/a"}, "d2h_us": {"p50_us": 17.216, "p95_us": 20.735, "p99_us": 21.312, "max_us": 21.632, "gate": "n/a"}, "gpu_process_us": {"p50_us": 102.379, "p95_us": 156.743, "p99_us": 162.969, "max_us": 289.237, "gate": "n/a"}}, "backend": "cuda", "iterations": 6132, "gpu_snap": {"mem_used_MiB": 1125, "mem_delta_MiB": 542, "pcie_gen": "5", "pcie_width": "4", "util_gpu_pct": 6, "util_mem_pct": 0, "graphics_clock_MHz": 2392, "mem_clock_MHz": 13801, "power_W": 50.59}, "nsys_error": "invalid literal for int() with base 10: '5236.5'"}
{"label": "m-to-n_M4_N16", "mode": "m-to-n", "M": 4, "N": 16, "metrics": {"model_mix_latency": {"p50_us": 1226.091, "p95_us": 4779.453, "p99_us": 4794.075, "max_us": 5214.919, "gate": "red"}, "h2d_us": {"p50_us": 64.159, "p95_us": 225.119, "p99_us": 230.015, "max_us": 339.455, "gate": "n/a"}, "kernel_us": {"p50_us": 6.591, "p95_us": 16.863, "p99_us": 16.928, "max_us": 96.767, "gate": "n/a"}, "d2h_us": {"p50_us": 17.823, "p95_us": 20.735, "p99_us": 21.056, "max_us": 21.376, "gate": "n/a"}, "gpu_process_us": {"p50_us": 102.425, "p95_us": 273.226, "p99_us": 277.454, "max_us": 385.089, "gate": "n/a"}}, "backend": "cuda", "iterations": 5180, "gpu_snap": {"mem_used_MiB": 1163, "mem_delta_MiB": 580, "pcie_gen": "5", "pcie_width": "4", "util_gpu_pct": 6, "util_mem_pct": 0, "graphics_clock_MHz": 2392, "mem_clock_MHz": 13801, "power_W": 50.96}, "nsys_error": "invalid literal for int() with base 10: '6105.8'"}
{"label": "m-to-n_M4_N2", "mode": "m-to-n", "M": 4, "N": 2, "metrics": {"model_mix_latency": {"p50_us": 636.33, "p95_us": 1229.655, "p99_us": 1237.128, "max_us": 2274.528, "gate": "red"}, "h2d_us": {"p50_us": 39.648, "p95_us": 65.311, "p99_us": 68.415, "max_us": 134.304, "gate": "n/a"}, "kernel_us": {"p50_us": 4.703, "p95_us": 6.688, "p99_us": 6.719, "max_us": 194.591, "gate": "n/a"}, "d2h_us": {"p50_us": 17.632, "p95_us": 20.064, "p99_us": 21.056, "max_us": 21.215, "gate": "n/a"}, "gpu_process_us": {"p50_us": 75.245, "p95_us": 102.515, "p99_us": 103.779, "max_us": 501.034, "gate": "n/a"}}, "backend": "cuda", "iterations": 12036, "gpu_snap": {"mem_used_MiB": 1099, "mem_delta_MiB": 516, "pcie_gen": "5", "pcie_width": "4", "util_gpu_pct": 7, "util_mem_pct": 0, "graphics_clock_MHz": 2392, "mem_clock_MHz": 13801, "power_W": 50.99}, "nsys_error": "invalid literal for int() with base 10: '3057.9'"}
{"label": "m-to-n_M8_N2", "mode": "m-to-n", "M": 8, "N": 2, "metrics": {"model_mix_latency": {"p50_us": 635.957, "p95_us": 2407.792, "p99_us": 2417.043, "max_us": 2576.293, "gate": "red"}, "h2d_us": {"p50_us": 38.72, "p95_us": 116.64, "p99_us": 119.999, "max_us": 184.992, "gate": "n/a"}, "kernel_us": {"p50_us": 4.672, "p95_us": 10.623, "p99_us": 10.751, "max_us": 224.767, "gate": "n/a"}, "d2h_us": {"p50_us": 14.911, "p95_us": 19.999, "p99_us": 21.023, "max_us": 21.215, "gate": "n/a"}, "gpu_process_us": {"p50_us": 75.442, "p95_us": 155.405, "p99_us": 163.279, "max_us": 301.061, "gate": "n/a"}}, "backend": "cuda", "iterations": 10130, "gpu_snap": {"mem_used_MiB": 1109, "mem_delta_MiB": 526, "pcie_gen": "5", "pcie_width": "4", "util_gpu_pct": 7, "util_mem_pct": 0, "graphics_clock_MHz": 2392, "mem_clock_MHz": 13801, "power_W": 50.81}, "nsys_error": "invalid literal for int() with base 10: '3517.2'"}
{"label": "m-to-n_M16_N2", "mode": "m-to-n", "M": 16, "N": 2, "metrics": {"model_mix_latency": {"p50_us": 639.543, "p95_us": 4817.822, "p99_us": 4832.746, "max_us": 5856.168, "gate": "red"}, "h2d_us": {"p50_us": 38.336, "p95_us": 224.031, "p99_us": 229.056, "max_us": 301.472, "gate": "n/a"}, "kernel_us": {"p50_us": 4.672, "p95_us": 16.672, "p99_us": 16.896, "max_us": 225.823, "gate": "n/a"}, "d2h_us": {"p50_us": 15.936, "p95_us": 20.064, "p99_us": 20.767, "max_us": 21.247, "gate": "n/a"}, "gpu_process_us": {"p50_us": 75.085, "p95_us": 271.138, "p99_us": 275.845, "max_us": 397.174, "gate": "n/a"}}, "backend": "cuda", "iterations": 9054, "gpu_snap": {"mem_used_MiB": 1129, "mem_delta_MiB": 546, "pcie_gen": "5", "pcie_width": "4", "util_gpu_pct": 6, "util_mem_pct": 0, "graphics_clock_MHz": 2392, "mem_clock_MHz": 13801, "power_W": 50.92}, "nsys_error": "invalid literal for int() with base 10: '3812.8'"}
{"label": "m-to-n_M8_N4", "mode": "m-to-n", "M": 8, "N": 4, "metrics": {"model_mix_latency": {"p50_us": 1238.502, "p95_us": 2431.385, "p99_us": 2440.286, "max_us": 3214.113, "gate": "red"}, "h2d_us": {"p50_us": 63.84, "p95_us": 118.079, "p99_us": 121.247, "max_us": 186.048, "gate": "n/a"}, "kernel_us": {"p50_us": 6.655, "p95_us": 10.688, "p99_us": 10.751, "max_us": 210.015, "gate": "n/a"}, "d2h_us": {"p50_us": 17.632, "p95_us": 20.896, "p99_us": 21.088, "max_us": 21.215, "gate": "n/a"}, "gpu_process_us": {"p50_us": 102.264, "p95_us": 157.631, "p99_us": 163.22, "max_us": 311.986, "gate": "n/a"}}, "backend": "cuda", "iterations": 6132, "gpu_snap": {"mem_used_MiB": 1125, "mem_delta_MiB": 542, "pcie_gen": "5", "pcie_width": "4", "util_gpu_pct": 6, "util_mem_pct": 0, "graphics_clock_MHz": 2392, "mem_clock_MHz": 13801, "power_W": 50.73}, "nsys_error": "invalid literal for int() with base 10: '5219.6'"}
{"label": "m-to-n_M16_N4", "mode": "m-to-n", "M": 16, "N": 4, "metrics": {"model_mix_latency": {"p50_us": 1233.869, "p95_us": 4816.351, "p99_us": 4831.151, "max_us": 5130.068, "gate": "red"}, "h2d_us": {"p50_us": 63.263, "p95_us": 224.895, "p99_us": 230.112, "max_us": 233.728, "gate": "n/a"}, "kernel_us": {"p50_us": 6.624, "p95_us": 16.704, "p99_us": 16.896, "max_us": 187.904, "gate": "n/a"}, "d2h_us": {"p50_us": 17.888, "p95_us": 20.927, "p99_us": 21.183, "max_us": 21.471, "gate": "n/a"}, "gpu_process_us": {"p50_us": 102.082, "p95_us": 272.835, "p99_us": 279.377, "max_us": 1409.523, "gate": "n/a"}}, "backend": "cuda", "iterations": 5140, "gpu_snap": {"mem_used_MiB": 1161, "mem_delta_MiB": 578, "pcie_gen": "5", "pcie_width": "4", "util_gpu_pct": 6, "util_mem_pct": 0, "graphics_clock_MHz": 2392, "mem_clock_MHz": 13801, "power_W": 50.58}, "nsys_error": "invalid literal for int() with base 10: '6101.0'"}
{"label": "tdl-a_E2", "mode": "static-tdl-a", "M": 1, "N": 2, "metrics": {"model_mix_latency": {"p50_us": 7321.702, "p95_us": 7348.475, "p99_us": 7829.971, "max_us": 8510.47, "gate": "red"}, "h2d_us": {"p50_us": 21.983, "p95_us": 25.407, "p99_us": 27.424, "max_us": 95.264, "gate": "n/a"}, "kernel_us": {"p50_us": 2.687, "p95_us": 4.416, "p99_us": 4.511, "max_us": 283.903, "gate": "n/a"}, "d2h_us": {"p50_us": 16.64, "p95_us": 19.711, "p99_us": 19.743, "max_us": 20.767, "gate": "n/a"}, "gpu_process_us": {"p50_us": 54.645, "p95_us": 56.665, "p99_us": 61.002, "max_us": 341.085, "gate": "n/a"}}, "backend": "cuda", "iterations": 1366, "gpu_snap": {"mem_used_MiB": 1091, "mem_delta_MiB": 508, "pcie_gen": "5", "pcie_width": "4", "util_gpu_pct": 0, "util_mem_pct": 0, "graphics_clock_MHz": 2392, "mem_clock_MHz": 13801, "power_W": 49.96}, "nsys_error": "invalid literal for int() with base 10: '1329.4'"}
{"label": "tdl-a_E16", "mode": "static-tdl-a", "M": 8, "N": 16, "metrics": {"model_mix_latency": {"p50_us": 7267.44, "p95_us": 57860.515, "p99_us": 57997.823, "max_us": 58251.813, "gate": "red"}, "h2d_us": {"p50_us": 23.296, "p95_us": 116.319, "p99_us": 121.44, "max_us": 122.975, "gate": "n/a"}, "kernel_us": {"p50_us": 4.416, "p95_us": 6.399, "p99_us": 6.527, "max_us": 141.984, "gate": "n/a"}, "d2h_us": {"p50_us": 14.592, "p95_us": 18.656, "p99_us": 19.711, "max_us": 20.671, "gate": "n/a"}, "gpu_process_us": {"p50_us": 56.155, "p95_us": 152.098, "p99_us": 157.421, "max_us": 292.001, "gate": "n/a"}}, "backend": "cuda", "iterations": 783, "gpu_snap": {"mem_used_MiB": 1099, "mem_delta_MiB": 516, "pcie_gen": "5", "pcie_width": "4", "util_gpu_pct": 0, "util_mem_pct": 0, "graphics_clock_MHz": 2392, "mem_clock_MHz": 13801, "power_W": 50.32}, "nsys_error": "invalid literal for int() with base 10: '1637.1'"}
